docannometa.py
docannometa-0.2.dist-info/WHEEL
docannometa-0.2.dist-info/METADATA
docannometa-0.2.dist-info/RECORD
