Metadata-Version: 2.1
Name: docannometa
Version: 0.2
Summary: Document symbols via annotation metadata, as described by PEP 727.
Author-email: Laurie O <laurie_opperman@hotmail.com>
Requires-Python: >= 3.6
Classifier: License :: OSI Approved :: MIT License
Project-URL: Source, https://github.com/EpicWink/python-docannometa
